README.md
setup.py
openkanji/__init__.py
openkanji.egg-info/PKG-INFO
openkanji.egg-info/SOURCES.txt
openkanji.egg-info/dependency_links.txt
openkanji.egg-info/top_level.txt